base_kivy_app/__init__.py
base_kivy_app/app.py
base_kivy_app/graphics.kv
base_kivy_app/graphics.py
base_kivy_app/utils.py
base_kivy_app/media/flat_icons/autorenew.png
base_kivy_app/media/flat_icons/calendar-text-outline.png
base_kivy_app/media/flat_icons/call-split.png
base_kivy_app/media/flat_icons/checkbox-blank-outline.png
base_kivy_app/media/flat_icons/checkbox-intermediate.png
base_kivy_app/media/flat_icons/chevron-down.png
base_kivy_app/media/flat_icons/chevron-right.png
base_kivy_app/media/flat_icons/content-save-move.png
base_kivy_app/media/flat_icons/eraser.png
base_kivy_app/media/flat_icons/error.png
base_kivy_app/media/flat_icons/eye-off.png
base_kivy_app/media/flat_icons/eye.png
base_kivy_app/media/flat_icons/flat_add_to_selection.png
base_kivy_app/media/flat_icons/flat_alert.png
base_kivy_app/media/flat_icons/flat_align.png
base_kivy_app/media/flat_icons/flat_arrow_down.png
base_kivy_app/media/flat_icons/flat_arrow_down_bold.png
base_kivy_app/media/flat_icons/flat_arrow_right.png
base_kivy_app/media/flat_icons/flat_arrow_up_bold.png
base_kivy_app/media/flat_icons/flat_blank_checkbox.png
base_kivy_app/media/flat_icons/flat_camera_switch.png
base_kivy_app/media/flat_icons/flat_chart_line.png
base_kivy_app/media/flat_icons/flat_check_checkbox.png
base_kivy_app/media/flat_icons/flat_circle.png
base_kivy_app/media/flat_icons/flat_copy.png
base_kivy_app/media/flat_icons/flat_delete.png
base_kivy_app/media/flat_icons/flat_dots_horizontal.png
base_kivy_app/media/flat_icons/flat_dots_vertical.png
base_kivy_app/media/flat_icons/flat_download.png
base_kivy_app/media/flat_icons/flat_drag_horizontal.png
base_kivy_app/media/flat_icons/flat_drag_vertical.png
base_kivy_app/media/flat_icons/flat_dropdown.png
base_kivy_app/media/flat_icons/flat_ellipse.png
base_kivy_app/media/flat_icons/flat_folder.png
base_kivy_app/media/flat_icons/flat_fullscreen.png
base_kivy_app/media/flat_icons/flat_fullscreen_exit.png
base_kivy_app/media/flat_icons/flat_info.png
base_kivy_app-0.1.3.dist-info/licenses/LICENSE
base_kivy_app-0.1.3.dist-info/METADATA
base_kivy_app-0.1.3.dist-info/WHEEL
base_kivy_app-0.1.3.dist-info/top_level.txt
base_kivy_app-0.1.3.dist-info/RECORD
